<nav search_view="search">

  <view name="landing" default='true' />
  <view name="search"/>
  <view name="setup_page"/>
  <a href="../../../en-US/manager/rest_ta/data/inputs/rest" target="_blank">Data Inputs</a>
  <a href="https://www.baboonbones.com/php/markdown.php?document=rest/README.md" target="_blank">Documentation</a>

  <collection label="Logs">
    <a href="../../../en-US/app/rest_ta/search?q=search%20index%3D_internal%20source%3D*restmodinput_app_modularinput.log*" target="_blank">Mod Input Script Logs</a>
    <a href="../../../en-US/app/rest_ta/search?q=search%20index%3D_internal%20source%3D*restmodinput_app_setuphandler.log*" target="_blank">Setup Logs</a>
    <a href="../../../en-US/app/rest_ta/search?q=search%20index%3D_internal%20error%20rest.py" target="_blank">Splunk Internal Logs</a>
  </collection>

  <a href="https://www.baboonbones.com/#support" target="_blank">Support</a>
  <a href="https://www.baboonbones.com" target="_blank">BaboonBones Website</a>
       
</nav>